{
  "ifeiSub": 37500,
  "ceylanSub": 1250000,
  "date": "2023/12/8 上午1:09:56",
  "viewCount": 1276216,
  "videoCount": 21,
  "mostView": {
    "title": "我做了首來鬧的抖音舞曲",
    "videoId": "aZII8BYkiRg",
    "description": "",
    "thumbnail": "https://i.ytimg.com/vi/aZII8BYkiRg/hqdefault.jpg",
    "releaseDate": "2023-11-04T09:23:01Z"
  },
  "latestVideo": {
    "title": "一個普通高中生的房間",
    "videoId": "Bcx9OXOOqDQ",
    "description": "我住在城堡//蘇爾連帽拉鏈外套▻ https://ifeisu.cashier.ecpay.com.tw/product/000000000552666 //設備Mac Studio M2 MAX ...",
    "thumbnail": "https://i.ytimg.com/vi/Bcx9OXOOqDQ/hqdefault.jpg",
    "releaseDate": "2023-11-26T23:58:59Z"
  },
  "latestComment": {
    "comment": "想收5d 念設計系只能用4000d頗可憐",
    "author": "@user-ks9ks4mr4i",
    "authorProfile": "http://www.youtube.com/channel/UCIVlRQBm9SfYT896-7s6gjw",
    "authorProfilePhoto": "https://yt3.ggpht.com/ytc/APkrFKZe4qfg5ulU34_Tf2WyT5cxEQsmx5S_cIoV5J8mCcM=s48-c-k-c0x00ffffff-no-rj"
  }
}