{
  "ifeiSub": 47500,
  "ceylanSub": 1270000,
  "date": "2024/2/8 下午6:10:21",
  "viewCount": 1565668,
  "videoCount": 28,
  "mostView": {
    "title": "我做了首來鬧的抖音舞曲",
    "videoId": "xqEbgLmRBD0",
    "description": "Patreon會員: 包含每週Podcast，幕後花絮，每月Vlog和其他獨家內容https://patreon.com/ifei //社交媒體: Instagram: ...",
    "thumbnail": "https://i.ytimg.com/vi/xqEbgLmRBD0/hqdefault.jpg",
    "releaseDate": "2023-11-16T18:00:21Z"
  },
  "latestVideo": {
    "title": "我做了首不存在的動漫OP 2",
    "videoId": "Ux-B7WzBGXs",
    "description": "",
    "thumbnail": "https://i.ytimg.com/vi/Ux-B7WzBGXs/hqdefault.jpg",
    "releaseDate": "2024-02-05T18:15:46Z"
  },
  "latestComment": {
    "comment": "幹 玩原神喔 這整個台北市的房子給我我都虧很大欸",
    "author": "@user-po9pd2fj8h",
    "authorProfile": "http://www.youtube.com/@user-po9pd2fj8h",
    "authorProfilePhoto": "https://yt3.ggpht.com/YicDY6oCvhNKWA9OzNQxDOaFz0pkFB_zc8TRcBkF_X4rind-sxX5yKe2JdGO42gdYt_z3d9qpyA=s48-c-k-c0x00ffffff-no-rj"
  }
}