{
  "ifeiSub": 62400,
  "ceylanSub": 1290000,
  "date": "2024/4/30 下午6:34:52",
  "viewCount": 3434275,
  "videoCount": 39,
  "mostView": {
    "title": "我做了首不存在的動漫OP",
    "videoId": "G4_28MUBgoI",
    "description": "",
    "thumbnail": "https://i.ytimg.com/vi/G4_28MUBgoI/hqdefault.jpg",
    "releaseDate": "2024-02-01T09:35:04Z"
  },
  "latestVideo": {
    "title": "我幫傳說對決寫了一首歌",
    "videoId": "HUu6ixsbBq8",
    "description": "",
    "thumbnail": "https://i.ytimg.com/vi/HUu6ixsbBq8/hqdefault.jpg",
    "releaseDate": "2024-04-29T16:00:22Z"
  },
  "latestComment": {
    "comment": "你叫什麼名子我想加你好友",
    "author": "@user-hb9mi9qk4m",
    "authorProfile": "http://www.youtube.com/@user-hb9mi9qk4m",
    "authorProfilePhoto": "https://yt3.ggpht.com/ytc/AIdro_kHAm2ixJDfGASyEhu7WuqSkLn_4DcM2vLChLj2HOc=s48-c-k-c0x00ffffff-no-rj"
  }
}