{
  "ifeiSub": 64900,
  "ceylanSub": 1300000,
  "date": "2024/7/13 下午3:32:03",
  "viewCount": 3831646,
  "videoCount": 60,
  "mostView": {
    "title": "我做了首不存在的動漫OP",
    "videoId": "G4_28MUBgoI",
    "description": "",
    "thumbnail": "https://i.ytimg.com/vi/G4_28MUBgoI/hqdefault.jpg",
    "releaseDate": "2024-02-01T09:35:04Z"
  },
  "latestVideo": {
    "title": "蘇裔非 - 在妳之前 MV",
    "videoId": "UureE5Wsfto",
    "description": "完整版影片: https://youtu.be/kEt8cjK50gc [mv] 導演: 妙妙懶爵剪輯: 黃聿謙、妙妙懶爵副導: MGS [music] 作曲: 蘇裔非作詞: 蘇裔非, ...",
    "thumbnail": "https://i.ytimg.com/vi/UureE5Wsfto/hqdefault.jpg",
    "releaseDate": "2024-07-11T16:49:12Z"
  },
  "latestComment": {
    "comment": "還以為會唱出什麼<br>結果就是跟羅恩他們差不多的拉基歌...",
    "author": "@LLLLLL-vu1kx",
    "authorProfile": "http://www.youtube.com/@LLLLLL-vu1kx",
    "authorProfilePhoto": "https://yt3.ggpht.com/ytc/AIdro_nZhB8D-pmLw0DqfYYSJFmO6XZZYdn3UbwQeS1q0z1D58l2icD3fRIfUNwuWHdj8M2-MA=s48-c-k-c0x00ffffff-no-rj"
  }
}