{
  "ifeiSub": 40800,
  "ceylanSub": 1260000,
  "date": "2024/1/18 上午12:39:03",
  "viewCount": 963288,
  "videoCount": 19,
  "mostView": {
    "title": "我做了首來鬧的抖音舞曲",
    "videoId": "xqEbgLmRBD0",
    "description": "YouTube爸爸別限我流。 https://youtu.be/NlTziQoypiU 剪輯: 蘇裔非、DANIELKIN 商業信箱: ifeibusiness@gmail.com Instagram: ...",
    "thumbnail": "https://i.ytimg.com/vi/xqEbgLmRBD0/hqdefault.jpg",
    "releaseDate": "2023-11-16T18:00:21Z"
  },
  "latestVideo": {
    "title": "你可以幫我做一首廣告歌嗎？",
    "videoId": "F7tQn3ains0",
    "description": "",
    "thumbnail": "https://i.ytimg.com/vi/F7tQn3ains0/hqdefault.jpg",
    "releaseDate": "2024-01-14T01:00:07Z"
  },
  "latestComment": {
    "comment": "超愛8bit鼓機",
    "author": "@Alger304",
    "authorProfile": "http://www.youtube.com/channel/UCmnfP_OQ15CkpP2ij2W5HDA",
    "authorProfilePhoto": "https://yt3.ggpht.com/5c7eo75i-17LF8C1PBAvxOXC8-Ou-GGuyouUu2TbVqSmNGhaA784Sm33-EPJLOOGZRf3u14BVw=s48-c-k-c0x00ffffff-no-rj"
  }
}